botbuilder/testing/__init__.py
botbuilder/testing/about.py
botbuilder/testing/dialog_test_client.py
botbuilder/testing/dialog_test_logger.py
botbuilder/testing/storage_base_tests.py
botbuilder_testing-4.17.1.dist-info/METADATA
botbuilder_testing-4.17.1.dist-info/WHEEL
botbuilder_testing-4.17.1.dist-info/top_level.txt
botbuilder_testing-4.17.1.dist-info/RECORD
